<annotation>
	<folder>train</folder>
	<filename>191.jpg</filename>
	<path>C:\Users\Krishna\Desktop\test\customdetector\images\train\191.jpg</path>
	<source>
		<database>Unknown</database>
	</source>
	<size>
		<width>960</width>
		<height>1280</height>
		<depth>3</depth>
	</size>
	<segmented>0</segmented>
	<object>
		<name>numberplate</name>
		<pose>Unspecified</pose>
		<truncated>0</truncated>
		<difficult>0</difficult>
		<bndbox>
			<xmin>343</xmin>
			<ymin>949</ymin>
			<xmax>602</xmax>
			<ymax>1021</ymax>
		</bndbox>
	</object>
</annotation>
