<annotation>
	<folder>train</folder>
	<filename>34.jpg</filename>
	<path>C:\Users\Krishna\Desktop\test\customdetector\images\train\34.jpg</path>
	<source>
		<database>Unknown</database>
	</source>
	<size>
		<width>3720</width>
		<height>2472</height>
		<depth>3</depth>
	</size>
	<segmented>0</segmented>
	<object>
		<name>numberplate</name>
		<pose>Unspecified</pose>
		<truncated>0</truncated>
		<difficult>0</difficult>
		<bndbox>
			<xmin>1217</xmin>
			<ymin>967</ymin>
			<xmax>2480</xmax>
			<ymax>1309</ymax>
		</bndbox>
	</object>
</annotation>
