<annotation>
	<folder>train1</folder>
	<filename>img87.jpg</filename>
	<path>C:\Users\Krishna\Desktop\numberplatedetection\images\train1\img87.jpg</path>
	<source>
		<database>Unknown</database>
	</source>
	<size>
		<width>1920</width>
		<height>1440</height>
		<depth>3</depth>
	</size>
	<segmented>0</segmented>
	<object>
		<name>numberplate</name>
		<pose>Unspecified</pose>
		<truncated>0</truncated>
		<difficult>0</difficult>
		<bndbox>
			<xmin>198</xmin>
			<ymin>2</ymin>
			<xmax>1089</xmax>
			<ymax>324</ymax>
		</bndbox>
	</object>
	<object>
		<name>numberplate</name>
		<pose>Unspecified</pose>
		<truncated>0</truncated>
		<difficult>0</difficult>
		<bndbox>
			<xmin>189</xmin>
			<ymin>233</ymin>
			<xmax>1123</xmax>
			<ymax>566</ymax>
		</bndbox>
	</object>
	<object>
		<name>numberplate</name>
		<pose>Unspecified</pose>
		<truncated>0</truncated>
		<difficult>0</difficult>
		<bndbox>
			<xmin>138</xmin>
			<ymin>566</ymin>
			<xmax>1096</xmax>
			<ymax>822</ymax>
		</bndbox>
	</object>
	<object>
		<name>numberplate</name>
		<pose>Unspecified</pose>
		<truncated>0</truncated>
		<difficult>0</difficult>
		<bndbox>
			<xmin>140</xmin>
			<ymin>828</ymin>
			<xmax>1129</xmax>
			<ymax>1120</ymax>
		</bndbox>
	</object>
	<object>
		<name>numberplate</name>
		<pose>Unspecified</pose>
		<truncated>1</truncated>
		<difficult>0</difficult>
		<bndbox>
			<xmin>225</xmin>
			<ymin>1177</ymin>
			<xmax>1027</xmax>
			<ymax>1440</ymax>
		</bndbox>
	</object>
	<object>
		<name>numberplate</name>
		<pose>Unspecified</pose>
		<truncated>0</truncated>
		<difficult>0</difficult>
		<bndbox>
			<xmin>1245</xmin>
			<ymin>188</ymin>
			<xmax>1860</xmax>
			<ymax>437</ymax>
		</bndbox>
	</object>
	<object>
		<name>numberplate</name>
		<pose>Unspecified</pose>
		<truncated>0</truncated>
		<difficult>0</difficult>
		<bndbox>
			<xmin>1276</xmin>
			<ymin>382</ymin>
			<xmax>1867</xmax>
			<ymax>553</ymax>
		</bndbox>
	</object>
	<object>
		<name>numberplate</name>
		<pose>Unspecified</pose>
		<truncated>0</truncated>
		<difficult>0</difficult>
		<bndbox>
			<xmin>1303</xmin>
			<ymin>557</ymin>
			<xmax>1885</xmax>
			<ymax>751</ymax>
		</bndbox>
	</object>
	<object>
		<name>numberplate</name>
		<pose>Unspecified</pose>
		<truncated>0</truncated>
		<difficult>0</difficult>
		<bndbox>
			<xmin>1314</xmin>
			<ymin>731</ymin>
			<xmax>1916</xmax>
			<ymax>917</ymax>
		</bndbox>
	</object>
	<object>
		<name>numberplate</name>
		<pose>Unspecified</pose>
		<truncated>0</truncated>
		<difficult>0</difficult>
		<bndbox>
			<xmin>1374</xmin>
			<ymin>900</ymin>
			<xmax>1909</xmax>
			<ymax>1086</ymax>
		</bndbox>
	</object>
</annotation>
