<annotation>
	<folder>train</folder>
	<filename>IMG_20180917_154148.jpg</filename>
	<path>C:\Users\Krishna\Desktop\test\customdetector\images\train\IMG_20180917_154148.jpg</path>
	<source>
		<database>Unknown</database>
	</source>
	<size>
		<width>2441</width>
		<height>825</height>
		<depth>3</depth>
	</size>
	<segmented>0</segmented>
	<object>
		<name>numberplate</name>
		<pose>Unspecified</pose>
		<truncated>0</truncated>
		<difficult>0</difficult>
		<bndbox>
			<xmin>152</xmin>
			<ymin>133</ymin>
			<xmax>2238</xmax>
			<ymax>661</ymax>
		</bndbox>
	</object>
</annotation>
