<annotation>
	<folder>train</folder>
	<filename>IMG_20180917_154434.jpg</filename>
	<path>C:\Users\Krishna\Desktop\test\customdetector\images\train\IMG_20180917_154434.jpg</path>
	<source>
		<database>Unknown</database>
	</source>
	<size>
		<width>2569</width>
		<height>869</height>
		<depth>3</depth>
	</size>
	<segmented>0</segmented>
	<object>
		<name>numberplate</name>
		<pose>Unspecified</pose>
		<truncated>0</truncated>
		<difficult>0</difficult>
		<bndbox>
			<xmin>47</xmin>
			<ymin>149</ymin>
			<xmax>2480</xmax>
			<ymax>767</ymax>
		</bndbox>
	</object>
</annotation>
