<annotation>
	<folder>train</folder>
	<filename>IMG_20181115_113940.jpg</filename>
	<path>C:\Users\Krishna\Desktop\test\customdetector\images\train\IMG_20181115_113940.jpg</path>
	<source>
		<database>Unknown</database>
	</source>
	<size>
		<width>1769</width>
		<height>769</height>
		<depth>3</depth>
	</size>
	<segmented>0</segmented>
	<object>
		<name>numberplate</name>
		<pose>Unspecified</pose>
		<truncated>0</truncated>
		<difficult>0</difficult>
		<bndbox>
			<xmin>92</xmin>
			<ymin>57</ymin>
			<xmax>1714</xmax>
			<ymax>682</ymax>
		</bndbox>
	</object>
</annotation>
